easy_bounding_box/__init__.py
easy_bounding_box/box.py
easy_bounding_box/utils/__init__.py
easy_bounding_box/utils/box_utils.py
tests/__init__.py
tests/test_box.py
tests/test_box_utils.py
easy_bounding_box-0.0.5.dist-info/LICENCE
easy_bounding_box-0.0.5.dist-info/METADATA
easy_bounding_box-0.0.5.dist-info/WHEEL
easy_bounding_box-0.0.5.dist-info/top_level.txt
easy_bounding_box-0.0.5.dist-info/RECORD
