Metadata-Version: 2.1
Name: easy-bounding-box
Version: 0.0.5
Summary: Package to simplify bounding boxes usage
Home-page: https://github.com/LucasLCO/easy_bounding_box
Author: LucasLCO
Author-email: lucaslco2005@gmail.com
Classifier: Programming Language :: Python :: 3
Classifier: License :: OSI Approved :: MIT License
Classifier: Operating System :: OS Independent
Requires-Python: >=3.7
License-File: LICENCE
